README.md
setup.cfg
setup.py
ghzh/__init__.py
ghzh/github/__init__.py
ghzh/github/client.py
ghzh/github/models.py
ghzh/zenhub/__init__.py
ghzh/zenhub/client.py
ghzh_clients.egg-info/PKG-INFO
ghzh_clients.egg-info/SOURCES.txt
ghzh_clients.egg-info/dependency_links.txt
ghzh_clients.egg-info/not-zip-safe
ghzh_clients.egg-info/requires.txt
ghzh_clients.egg-info/top_level.txt