Metadata-Version: 1.0
Name: ghzh-clients
Version: 0.1.1.dev0
Summary: A library that combines GitHub and ZenHub clients used for various OpenStax reports
Home-page: https://github.com/openstax/ghzh-clients
Author: m1yag1
Author-email: qa@openstax.org
License: AGPLv3
Platform: UNKNOWN
